nseazy/__init__.py
nseazy/_generate_request.py
nseazy/_help.py
nseazy/_helpers.py
nseazy/_instruments.py
nseazy/_validators.py
nseazy/_version.py
nseazy/fetch.py
nseazy-0.0.1b5.dist-info/LICENSE
nseazy-0.0.1b5.dist-info/METADATA
nseazy-0.0.1b5.dist-info/WHEEL
nseazy-0.0.1b5.dist-info/top_level.txt
nseazy-0.0.1b5.dist-info/RECORD
